featureprobe/__init__.py
featureprobe/access_recorder.py
featureprobe/client.py
featureprobe/config.py
featureprobe/context.py
featureprobe/data_repository.py
featureprobe/default_event_processor.py
featureprobe/detail.py
featureprobe/evaluation_result.py
featureprobe/event.py
featureprobe/event_processor.py
featureprobe/file_synchronizer.py
featureprobe/hit_result.py
featureprobe/http_config.py
featureprobe/memory_data_repository.py
featureprobe/polling_synchronizer.py
featureprobe/realtime.py
featureprobe/streaming_synchronizer.py
featureprobe/synchronizer.py
featureprobe/user.py
featureprobe/internal/__init__.py
featureprobe/internal/defaultable.py
featureprobe/internal/deprecated.py
featureprobe/internal/empty_str.py
featureprobe/internal/json_decoder.py
featureprobe/internal/semver.py
featureprobe/internal/serializable.py
featureprobe/internal/stringifiable.py
featureprobe/model/__init__.py
featureprobe/model/condition.py
featureprobe/model/distribution.py
featureprobe/model/predicate.py
featureprobe/model/prerequisite.py
featureprobe/model/repository.py
featureprobe/model/rule.py
featureprobe/model/segment.py
featureprobe/model/serve.py
featureprobe/model/split.py
featureprobe/model/toggle.py
featureprobe/predicate/__init__.py
featureprobe_server_sdk_python-2.2.1.dist-info/LICENSE
featureprobe_server_sdk_python-2.2.1.dist-info/METADATA
featureprobe_server_sdk_python-2.2.1.dist-info/WHEEL
featureprobe_server_sdk_python-2.2.1.dist-info/top_level.txt
featureprobe_server_sdk_python-2.2.1.dist-info/RECORD
