Metadata-Version: 2.1
Name: featureprobe-server-sdk-python
Version: 2.2.1
Summary: FeatureProbe Server Side SDK for Python
Author: FeatureProbe
License: Apache 2.0
Project-URL: Project Homepage, https://github.com/FeatureProbe
Project-URL: Source Code, https://github.com/FeatureProbe/server-sdk-python
Project-URL: Bug Reports, https://github.com/FeatureProbe/server-sdk-python/issues
Keywords: feature management,server sdk
Classifier: License :: OSI Approved :: Apache Software License
Classifier: Operating System :: OS Independent
Classifier: Programming Language :: Python :: 3 :: Only
Classifier: Programming Language :: Python :: 3.5
Classifier: Programming Language :: Python :: 3.6
Classifier: Programming Language :: Python :: 3.7
Classifier: Programming Language :: Python :: 3.8
Classifier: Programming Language :: Python :: 3.9
Classifier: Programming Language :: Python :: 3.10
Classifier: Development Status :: 5 - Production/Stable
Requires-Python: >=3.5, <4
License-File: LICENSE
Requires-Dist: APScheduler ~=3.0
Requires-Dist: requests >=2.12.0
Requires-Dist: tzlocal ~=2.0.0
Requires-Dist: python-socketio ~=5.3 ; python_version >= "3.6"
Requires-Dist: websocket-client ~=1.2 ; python_version >= "3.6"
